[{"time":"1573317049.572","nick":"ⓢ jackymaxj","msg":"啊，那是另一件事www"},{"time":"1573334157.237","nick":"ⓢ kshuan9","msg":"現在連中華台北都不給你用了今年青島 J80 帆船賽 台灣隊直接被迫改名成中「國」台北了: <a href=\"https://files.slack.com/files-pri/T02G2SXKM-FQCCGRPGV/download/image_from_ios.jpg\">https://files.slack.com/files-pri/T02G2SXKM-FQCCGRPGV/download/image_from_ios.jpg</a>"},{"time":"1573334157.992","nick":"ⓢ kshuan9","msg":"<a href=\"https://files.slack.com/files-pri/T02G2SXKM-FQCC9174G/download/image_from_ios.jpg\">https://files.slack.com/files-pri/T02G2SXKM-FQCC9174G/download/image_from_ios.jpg</a>"},{"time":"1573342269.472","nick":"ⓢ system","msg":"@chinkuei.office has joined the channel"},{"time":"1573396502.848","nick":"ⓢ Michael_li","msg":"@giallino 感謝你的資訊，我縮小搜尋目標，已經找齊所有資訊，可以開始比對了。"},{"time":"1573396503.118","nick":"ⓢ ↵","msg":"Michael_li@slack-legacy: "}]