[{"time":"1514321189.006","nick":"ⓢ patcon","msg":"To clarify, I wasn't able to make it either (had a ticket, but couldn't afford flight). But I'm really excited to connect Taiwanese g0v people with my good friends who are going! They are representing various groups like meshnet, civictech, toronto in general, and also they are wonderful open leadership practitioners, and care about supporting processes (like it seems g0v is very very great at) :)"},{"time":"1514321276.138","nick":"ⓢ patcon","msg":"Related: I'll hopefully make it to Taiwan sometime in the next 4 months, and would be so grateful to meet you wonderful folks in person then!"},{"time":"1514335063.849","nick":"ⓢ achemistd","msg":"感覺是純愛故事"},{"time":"1514359545.595","nick":"ⓢ clkao","msg":"@tkirby 競爭對手出現了! <a href=\"https://airbnb.design/lottie/\">https://airbnb.design/lottie/</a>"},{"time":"1514359546.801","nick":"kcwu","msg":"slackbot17's url: [Lottie]"},{"time":"1514360754.009","nick":"ⓢ yurenju","msg":"!!"},{"time":"1514367033.310","nick":"ⓢ hcchien","msg":"@clkao 的立委質詢跟投票記錄資料有了嗎"},{"time":"1514385813.157","nick":"ZXGUNIQUE_","msg":"hello？"},{"time":"1514388181.998","nick":"ⓢ johnny","msg":"投票指南有院會的投票紀錄"},{"time":"1514388183.030","nick":"ⓢ ↵","msg":"<a href=\"https://vote.ly.g0v.tw/api/vote/\">https://vote.ly.g0v.tw/api/vote/</a>"},{"time":"1514388184.514","nick":"kcwu","msg":"slackbot17's url: [Django REST framework]"}]