[{"time":"1436285460.066","nick":"ⓢ yurenju","msg":"okay cool."},{"time":"1436287226.135","nick":"ⓢ miaoski","msg":"acechen: 我現在在家裡試跑... 看用行動電源可以撐多久。不過 DN7C3CA006 從 A0 讀進來會漂，感覺很不妙。半夜的 PM2.5 應該不會一直變才對..."},{"time":"1436287245.167","nick":"ⓢ miaoski","msg":"倒是 MQ9 在 A1 的電壓一直很穩"},{"time":"1436287278.251","nick":"ⓢ miaoski","msg":"DHT-22 的濕度計一定有問題，它寫窗外 RH 50% 這根本不是台北市可能遇到的濕度。"},{"time":"1436287293.284","nick":"ⓢ miaoski","msg":"溫度 31.9 - 32.1 我想應該是可信的..."},{"time":"1436287387.326","nick":"ⓢ miaoski","msg":"如果你有空的話，看能不能幫我看一下電路有沒有哪裡有問題，還是需要再加 decouple ，還是其實我讀值的方法和 spec 寫的不一樣"},{"time":"1436287460.460","nick":"ⓢ miaoski","msg":"感謝。"},{"time":"1436317314.017","nick":"ⓢ acechen","msg":"@miaoski++  ok我看看"},{"time":"1436317368.105","nick":"ⓢ miaoski","msg":"@acechen: 感謝。我沒畫 schematics 出來就是了.. :$ 我今天會試著改用 A2 來取樣，看是不是台版 Arduino 在害我"},{"time":"1436317416.245","nick":"ⓢ miaoski","msg":"然後按 spec 量測 PM2.5 需要風扇沒上電的時候量測 V0. 所以我今天也會做這件事。我手上買了兩顆 DN7C3CA006 可以順便測它們出廠的時候有沒有校準。"},{"time":"1436317448.225","nick":"ⓢ miaoski","msg":"從 spec 上來看似乎是抽測，所以可能會很頭痛... 如果 V0 每顆都不一樣的話，說不定要加校準用的電路。:("},{"time":"1436317477.268","nick":"ⓢ miaoski","msg":"畫 schematic 有沒有推薦的 OSS 或網站? :simple_smile:"},{"time":"1436319477.723","nick":"ⓢ t0mst0ne","msg":"國健署的opendata 平台"},{"time":"1436319478.699","nick":"ⓢ ↵","msg":"&lt;<a href=\"http://data.hpa.gov.tw/\">http://data.hpa.gov.tw/</a>&gt;"},{"time":"1436319484.383","nick":"kcwu","msg":"slackbot3's url: [歡迎 - 衛生福利部國民健康署開放資料平台]"},{"time":"1436319551.755","nick":"ⓢ t0mst0ne","msg":"昨天衛福部內有表示, &lt;<a href=\"http://很多資料都放到data.gov|xn--data-pm9f897agklhplnxam351a3xj.gov\">http://很多資料都放到data.gov|xn--data-pm9f897agklhplnxam351a3xj.gov</a>&gt; , 但是好像沒人用 ...."},{"time":"1436319552.776","nick":"ⓢ ↵","msg":"今天再看看, 才發現的確有好多 (瀏覽量是0)"},{"time":"1436319582.783","nick":"ⓢ t0mst0ne","msg":"癌症發生統計"},{"time":"1436319583.803","nick":"ⓢ ↵","msg":"&lt;<a href=\"http://data.hpa.gov.tw/dataset/52d223a259ba6de72ac9cb5c88e5e605\">http://data.hpa.gov.tw/dataset/52d223a259ba6de72ac9cb5c88e5e605</a>&gt;"},{"time":"1436319584.751","nick":"ⓢ ↵","msg":"看看有沒有dataset 可以做成 @muyueh  之前的展示 :stuck_out_tongue:"},{"time":"1436319585.231","nick":"kcwu","msg":"slackbot3's url: [癌症發生統計 - 資料集 - 衛生福利部國民健康署開放資料平台]"},{"time":"1436326661.193","nick":"ⓢ t0mst0ne","msg":"請問  @kiang &lt;<a href=\"http://data.hpa.gov.tw/dataset\">http://data.hpa.gov.tw/dataset</a>&gt; 這個要怎麼定期 clone &amp;amp; update ?"},{"time":"1436326685.235","nick":"ⓢ kiang","msg":"我都是硬寫爬蟲抓的"},{"time":"1436326699.240","nick":"ⓢ kiang","msg":"like &lt;<a href=\"https://github.com/kiang/data.fda.gov.tw-list\">https://github.com/kiang/data.fda.gov.tw-list</a>&gt;"},{"time":"1436326701.209","nick":"kcwu","msg":"slackbot3's url: [kiang/data.fda.gov.tw-list · GitHub]"},{"time":"1436326725.274","nick":"ⓢ kiang","msg":"ckan 應該會方便許多"},{"time":"1436327058.723","nick":"ⓢ t0mst0ne","msg":"所以@kiang 大概多久會run ㄧ次？"},{"time":"1436327074.736","nick":"ⓢ kiang","msg":"我目前是一天跑一次"},{"time":"1436327126.764","nick":"ⓢ t0mst0ne","msg":"瞭解，看起來hpa 也要來clone ㄧ下"},{"time":"1436327406.137","nick":"ⓢ kiang","msg":"t0mst0ne: 或者問問 @ronnywang 有沒有打算定時塞進 sheethub"},{"time":"1436328127.980","nick":"ⓢ t0mst0ne","msg":"真的琳琅滿目"},{"time":"1436328128.978","nick":"ⓢ ↵","msg":"歷年活產新生兒出生性別比.CSV : &lt;<a href=\"http://data.hpa.gov.tw/dataset/143070840753/resource/a519c937-2e5c-4049-ab01-211e14332dce\">http://data.hpa.gov.tw/dataset/143070840753/resource/a519c937-2e5c-4049-ab01-211e14332dce</a>&gt;"},{"time":"1436328130.013","nick":"ⓢ ↵","msg":"歷年出生性別比.csv :"},{"time":"1436328130.265","nick":"kcwu","msg":"slackbot3's url: [歷年活產新生兒出生性別比 - 歷年活產新生兒出生性別比.CSV - 衛生福利部國民健康署開放資料平台]"},{"time":"1436328130.922","nick":"ⓢ ↵","msg":"&lt;<a href=\"http://data.hpa.gov.tw/dataset/643dc4cbd516522c1ca5cd3d47ef1503/resource/e44b4450-76f7-4811-b405-9a0604e51729\">http://data.hpa.gov.tw/dataset/643dc4cbd516522c1ca5cd3d47ef1503/resource/e44b4450-76f7-4811-b405-9a0604e51729</a>&gt;"},{"time":"1436328131.979","nick":"ⓢ ↵","msg":"2個 csv 要 接龍 ...( 時間有 overlap )"},{"time":"1436328133.020","nick":"ⓢ ↵","msg":"然後也有按照地理來區分(102年活產新生兒出生性別比-依縣市別分.CSV) , 但只有102年"},{"time":"1436328133.977","nick":"ⓢ ↵","msg":"&lt;<a href=\"http://data.hpa.gov.tw/dataset/143070881977/resource/f1962d2e-9682-43a1-a13c-752dc01a464d\">http://data.hpa.gov.tw/dataset/143070881977/resource/f1962d2e-9682-43a1-a13c-752dc01a464d</a>&gt;"},{"time":"1436328134.912","nick":"kcwu","msg":"slackbot3's url: [102年活產新生兒出生性別比-依縣市別分 - 102年活產新生兒出生性別比-依縣市別分.CSV - 衛生福利部國民健康署開放資料平台]"},{"time":"1436328138.931","nick":"kcwu","msg":"slackbot3's url: [歷年出生性別比 - 歷年出生性別比.csv - 衛生福利部國民健康署開放資料平台]"},{"time":"1436329976.135","nick":"ⓢ miaoski","msg":"acechen: 我參考了這篇 &lt;<a href=\"http://www.howmuchsnow.com/arduino/airquality/\">http://www.howmuchsnow.com/arduino/airquality/</a>&gt; 現在讀數穩定了。"},{"time":"1436329977.633","nick":"kcwu","msg":"slackbot3's url: [Monitoring your Air Quality]"},{"time":"1436330017.306","nick":"ⓢ miaoski","msg":"不過 壞消息是，我手上有兩顆，在無風扇的情況下，一顆的讀數在 208-210 之間，另一顆在 230-240 之間"},{"time":"1436330038.281","nick":"ⓢ miaoski","msg":"表示它每一顆的 V0 都需要 calibration :disappointed:"},{"time":"1436330741.105","nick":"ⓢ miaoski","msg":"acechen: 耗電量是另一個問題。我昨晚跑了 8 小時，早上起來 5000mAh 的電池剩一半。"},{"time":"1436332992.794","nick":"ⓢ yurenju","msg":"今天用了 hackfoldr, 感覺或許可以做一個專門給 hackfoldr 的 ethercalc 編輯器"},{"time":"1436333005.842","nick":"ⓢ yurenju","msg":"這樣可以降低門檻"},{"time":"1436333221.995","nick":"ⓢ hychen","msg":"yurenju+++"},{"time":"1436333230.054","nick":"ⓢ hychen","msg":"真錢端強者"},{"time":"1436333711.578","nick":"ⓢ poga","msg":"yurenju++"},{"time":"1436336064.135","nick":"Guoboism","msg":"Hello"},{"time":"1436344288.239","nick":"ⓢ mrorz","msg":"Guoboism: hi"},{"time":"1436344518.547","nick":"ⓢ mrorz","msg":"是說現在有沒有幫 PDF 裡面的頁面做 permalink 的 web app 呢～？"},{"time":"1436344519.563","nick":"ⓢ ↵","msg":"political promise tracker 這裡想要直接把施政報告 PDF 裡的標題拉出來當政策，然後細節就只丟個到 PDF 檔案特定 section 的 permalink"},{"time":"1436344520.481","nick":"ⓢ ↵","msg":"這樣就可以用程式蓋出資料庫，以後再慢慢m/4人工檢視的部分 XD&quot;"},{"time":"1436344995.271","nick":"ⓢ ronnywang","msg":"@kiang, @t0mst0ne : 目前 sheethub 是有打算把各 portal 的資料都拉進來，然後除了定期更新讓大家可以直接下載方便的格式以外，也希望能把各 portal 的資料連結起來"},{"time":"1436345066.289","nick":"ⓢ ronnywang","msg":"&lt;<a href=\"https://sheethub.com/area.reference.tw/%E4%B8%AD%E8%8F%AF%E6%B0%91%E5%9C%8B%E8%A1%8C%E6%94%BF%E5%8D%80/linelink/09020\">https://sheethub.com/area.reference.tw/%E4%B8%AD%E8%8F%AF%E6%B0%91%E5%9C%8B%E8%A1%8C%E6%94%BF%E5%8D%80/linelink/09020</a>&gt;  像是現在 URI 頁也有哪些 sheet 有連結到這一筆資料的功能，這樣以後只要搜尋 &quot;金門 人口&quot; 就可以找到有連結到金門縣又有人口兩字欄位的資料"},{"time":"1436345109.333","nick":"ⓢ t0mst0ne","msg":"@ronnywang: ++"},{"time":"1436345290.395","nick":"ⓢ t0mst0ne","msg":"那請問您是否有人工看不同portal 資料集是否是重複？"},{"time":"1436345302.410","nick":"ⓢ mrorz","msg":"看到 @kiang 在 hackpad 提到選舉黃頁的中選會原始檔案的處理方式是，「網頁格式則是透過程式將 PDF 轉為網頁型態的版本。」"},{"time":"1436345303.525","nick":"ⓢ ↵","msg":"請問 PDF 轉網頁的部分大概是怎麼做的呢～？"},{"time":"1436345373.503","nick":"ⓢ ronnywang","msg":"t0mst0ne: 我現在是每個 portal 都各自爬各自的，但是就遇到重覆的很多，或者是像 <a href=\"http://data.gov.tw\">http://data.gov.tw</a> 有放了很多資料是各地方的集合，例如實價登錄各縣市 portal 都有放自己縣市的，但是 <a href=\"http://data.gov.tw\">http://data.gov.tw</a> 又放全部的"},{"time":"1436345375.704","nick":"kcwu","msg":"slackbot3's url (1/2): [政府資料開放平臺]"},{"time":"1436345403.539","nick":"ⓢ ronnywang","msg":"現在想先都各自放，但是之後就讓地方的資料直接加提示說可以去中央看，然後中央那邊透過 SQL 篩選該縣市的資料"},{"time":"1436345491.693","nick":"ⓢ kiang","msg":"@mrorz: 我是用 pdf2htmlEX 轉的"},{"time":"1436345628.909","nick":"ⓢ t0mst0ne","msg":"<a href=\"http://Data.how.gov.tw\">http://Data.how.gov.tw</a> 有些資料集也跟 <a href=\"http://data.gov.tw\">http://data.gov.tw</a> 重複"},{"time":"1436345659.884","nick":"ⓢ t0mst0ne","msg":"<a href=\"http://Data.hpa.gov.tw\">http://Data.hpa.gov.tw</a>"},{"time":"1436345664.039","nick":"kcwu","msg":"slackbot3's url: [歡迎 - 衛生福利部國民健康署開放資料平台]"},{"time":"1436345708.019","nick":"ⓢ mrorz","msg":"kiang: cool, pdf2htmlEX 的 github 上面寫說他是 inspired by PDF.js"},{"time":"1436345709.122","nick":"ⓢ ↵","msg":"不知道他跟 PDF.js 相比的優點有哪些呢"},{"time":"1436345764.046","nick":"ⓢ kiang","msg":"PDF.js 應該是線上瀏覽， pdf2htmlEX 直接轉成網頁格式，網頁格式相對友善吧？我沒真的用過 pdf.js"},{"time":"1436345904.289","nick":"ⓢ monaludao","msg":"題外話，請問這種jsp網頁要怎麼爬出每一頁的內容? (下載網址) &lt;<a href=\"http://www.planning.ntpc.gov.tw/ap/fdownload/fdownload2.jsp?mfkind_id=00038\">http://www.planning.ntpc.gov.tw/ap/fdownload/fdownload2.jsp?mfkind_id=00038</a>&gt;"},{"time":"1436345905.843","nick":"kcwu","msg":"slackbot3's url: [無標題文件]"},{"time":"1436346231.600","nick":"ⓢ mrorz","msg":":+1: 感謝～～"},{"time":"1436346271.613","nick":"ⓢ clkao","msg":"<a href=\"http://ignite.clkao.org\">http://ignite.clkao.org</a> 就是用 pdf.js"},{"time":"1436347282.847","nick":"ⓢ mrorz","msg":"看起來 pdf2htmlEX 做完 text extraction 之後有針對每塊文字的坐標稍微排序一下，所以文字塊在 html 裡的順序不是亂的，如果要拉文字出來的話比較合適"},{"time":"1436347283.946","nick":"ⓢ ↵","msg":"不過 pdf2htmlEX 好像要先做 server-side processing 這樣"},{"time":"1436347437.060","nick":"ⓢ mrorz","msg":"如果想要做一個 PDF permalink 的純前端 webapp，"},{"time":"1436347438.021","nick":"ⓢ ↵","msg":"例如說達成「瀏覽 &lt;<a href=\"http://hackpdf.github.io/&lt;某\">http://hackpdf.github.io/&lt;某</a>&gt; google drive 上的 PDF file ID&gt;#page-3  可以顯示那個 PDF 並且自動翻到第三頁」這樣的行為，用純 browser 就能跑的 pdf.js 可能會比較容易"},{"time":"1436347499.094","nick":"ⓢ mrorz","msg":"// 至於 google drive 公開檔案有沒有開放 CORS，可能還要再研究一下 orz"},{"time":"1436348293.035","nick":"ⓢ yhsiang","msg":"monaludao: 直接爬然後解析 table內容搜集好 那個下載的 a的 href"},{"time":"1436348346.207","nick":"ⓢ monaludao","msg":"@yhsiang: 直接爬也可以爬到第2~10頁的href嗎"},{"time":"1436348412.238","nick":"ⓢ yhsiang","msg":"可以啊 他的 那個 js 都寫在內容裡面 就是送個 post 按照格式去送就可以了"},{"time":"1436348465.229","nick":"ⓢ yhsiang","msg":"送 post 然後帶上 mfkind_id, mf_name, enpage  幾個參數"},{"time":"1436348608.445","nick":"ⓢ monaludao","msg":"@yhsiang: 喔喔 我試試看 謝謝"},{"time":"1436354800.806","nick":"ⓢ ronnywang","msg":"剛剛才用 pdftotext 把捷運今天公開的各站時刻表的 PDF 轉成 CSV ，有時候如果 PDF 文件格式還滿統一的話，用 pdftotext 轉成純文字再去處理純文字就滿夠用的了   &lt;<a href=\"https://sheethub.com/ronnywang/台北捷運班次時刻表\">https://sheethub.com/ronnywang/台北捷運班次時刻表</a>&gt;"},{"time":"1436354862.902","nick":"ⓢ ronnywang","msg":"程式碼放在 &lt;<a href=\"https://github.com/ronnywang/taipei-mrt-table\">https://github.com/ronnywang/taipei-mrt-table</a>&gt;"},{"time":"1436354864.530","nick":"kcwu","msg":"slackbot3's url: [ronnywang/taipei-mrt-table · GitHub]"},{"time":"1436361206.420","nick":"ⓢ clkao","msg":"ronnywang: 我懷疑他們已經有 gtfs…. 不然為何 google 上會有時刻"},{"time":"1436361423.731","nick":"ⓢ mrorz","msg":"ronnywang++ 不過看來 pdftotext 對桃園市的施政報告不太行 XD"},{"time":"1436361491.881","nick":"ⓢ mrorz","msg":"&lt;<a href=\"http://i.imgur.com/yjOpeRa.png\">http://i.imgur.com/yjOpeRa.png</a>&gt;"},{"time":"1436361710.132","nick":"ⓢ ronnywang","msg":"pdftotext 可以加上 -layout ，排版會好看一點 &lt;<a href=\"https://clbin.com/WSAN0\">https://clbin.com/WSAN0</a>&gt;"},{"time":"1436361939.334","nick":"ⓢ ronnywang","msg":"@clkao: google 的導航的捷運時刻是準確的? 我以為他只是大概估一下幾分鐘到幾分鐘一班耶"},{"time":"1436362000.416","nick":"ⓢ mrorz","msg":"`-layout` 的結果： &lt;<a href=\"http://i.imgur.com/Z3pkQ0g.png\">http://i.imgur.com/Z3pkQ0g.png</a>&gt;"},{"time":"1436362001.391","nick":"ⓢ ↵","msg":"看來這真的高難度 XD"},{"time":"1436362086.563","nick":"ⓢ kiang","msg":"這種自由編排的文字轉換出來都不太好看，除非固定格式且數量很多才會想辦法拆吧 XD"},{"time":"1436362114.577","nick":"ⓢ kiang","msg":"大絕招就是去掉所有空白，純粹餵給系統當 meta data ，如果有中文分詞系統就會舒服一點 XD"},{"time":"1436362123.609","nick":"ⓢ mrorz","msg":"不過我很好奇的是"},{"time":"1436362139.591","nick":"ⓢ mrorz","msg":"mac 的 preview 選取之後複製貼上同樣這段文字"},{"time":"1436362149.637","nick":"ⓢ mrorz","msg":"居然沒有重複的字"},{"time":"1436362160.615","nick":"ⓢ mrorz","msg":"像是這樣："},{"time":"1436362161.717","nick":"ⓢ ↵","msg":"```"},{"time":"1436362162.587","nick":"ⓢ ↵","msg":"(5)捷運綠線延伸至中壢火車站可行性研究"},{"time":"1436362163.681","nick":"ⓢ ↵","msg":"捷運綠線 G01 延伸至中壢火車站可形成口字型路網,以達健全桃 4"},{"time":"1436362164.703","nick":"ⓢ ↵","msg":"園都會區交通路網、提供更完整的大眾運輸服務及提升大眾運輸使用 率目標。"},{"time":"1436362165.685","nick":"ⓢ ↵","msg":"目前已就方案一─八德 G01 站起,經中山東路,接環中東路至機 場捷運 A23 站及方案二─八德 G01 站起,經中山東路,接龍東路,轉 龍岡路至機場捷運 A23 站,綜合研究評估延伸至中壢、平鎮地區之可 行性,以利報請交通部審查,預計 105 年底可行性研究通過行政院核 定。本計畫未來 5 年施政重點與期程規劃詳如下表 4。"},{"time":"1436362166.601","nick":"ⓢ ↵","msg":"```"},{"time":"1436362192.623","nick":"ⓢ mrorz","msg":"mac 的 preview 用了什麼神招來去掉重複的字呀 @@"},{"time":"1436362228.671","nick":"ⓢ ronnywang","msg":"本來 PDF 有重覆的字嗎?"},{"time":"1436362230.745","nick":"ⓢ mrorz","msg":"算 bounding box 之類的？"},{"time":"1436362231.673","nick":"ⓢ ↵","msg":"來試試看號稱專做學術論文的 pdf2htmlEX 好了"},{"time":"1436362250.771","nick":"ⓢ mrorz","msg":"我猜 pdftotext 會拆出重複的字，一定是 PDF 裡面有兩個重複的字沒錯"},{"time":"1436362308.882","nick":"ⓢ mrorz","msg":"我用 pdftotext -bbox，拆出來的 html 長這樣："},{"time":"1436362310.024","nick":"ⓢ ↵","msg":"```html"},{"time":"1436362310.757","nick":"ⓢ ↵","msg":"    &lt;word xMin=&quot;153.000000&quot; yMin=&quot;745.835700&quot; xMax=&quot;208.973062&quot; yMax=&quot;759.801720&quot;&gt;捷運綠線&lt;/word&gt;"},{"time":"1436362311.797","nick":"ⓢ ↵","msg":"    &lt;word xMin=&quot;212.280000&quot; yMin=&quot;745.835700&quot; xMax=&quot;233.246541&quot; yMax=&quot;759.801720&quot;&gt;G01&lt;/word&gt;"},{"time":"1436362312.844","nick":"ⓢ ↵","msg":"    &lt;word xMin=&quot;212.520000&quot; yMin=&quot;745.835700&quot; xMax=&quot;219.507200&quot; yMax=&quot;759.801720&quot;&gt;G&lt;/word&gt;"},{"time":"1436362313.753","nick":"ⓢ ↵","msg":"    &lt;word xMin=&quot;236.700000&quot; yMin=&quot;745.835700&quot; xMax=&quot;278.695867&quot; yMax=&quot;759.801720&quot;&gt;延伸至&lt;/word&gt;"},{"time":"1436362314.779","nick":"ⓢ ↵","msg":"    &lt;word xMin=&quot;265.140000&quot; yMin=&quot;745.835700&quot; xMax=&quot;335.084667&quot; yMax=&quot;759.801720&quot;&gt;至中壢火車&lt;/word&gt;"},{"time":"1436362315.823","nick":"ⓢ ↵","msg":"    &lt;word xMin=&quot;321.000000&quot; yMin=&quot;745.835700&quot; xMax=&quot;376.973062&quot; yMax=&quot;759.801720&quot;&gt;車站可形&lt;/word&gt;"},{"time":"1436362316.775","nick":"ⓢ ↵","msg":"```"},{"time":"1436362317.813","nick":"ⓢ ronnywang","msg":"pdftotext 會這樣斜下去我猜是因為他針對的是英文字的字寬，但是中文字寬一倍所以就一直被往下擠"},{"time":"1436362368.825","nick":"ⓢ ronnywang","msg":"然後他這份 PDF 又很怪，幾個中文字就一個 box ，而不是一整段一個 box (好像很多 PDF 都這樣)"},{"time":"1436362486.964","nick":"ⓢ mrorz","msg":"我覺得跟英文字字寬可能無關，主要是圖文混排的時候，PDF 裡的 object 們的 layout 會打亂"},{"time":"1436362504.045","nick":"ⓢ mrorz","msg":"因為只要不是圖文混排，pdftotext 就表現得非常完美"},{"time":"1436362505.049","nick":"ⓢ mrorz","msg":"&lt;<a href=\"http://i.imgur.com/LgdPbtP.jpg\">http://i.imgur.com/LgdPbtP.jpg</a>&gt;"},{"time":"1436362572.122","nick":"ⓢ mrorz","msg":"在 object 被打亂的時候，就變成做 text extraction 的軟體要非常小心翼翼地處理各種狀況"},{"time":"1436362591.209","nick":"ⓢ mrorz","msg":"mac 的 preview 的複製貼上功能，裡面大概做了不少苦功"},{"time":"1436362596.127","nick":"ⓢ mrorz","msg":"工"},{"time":"1436362610.206","nick":"ⓢ kiang","msg":"之前試過去算 bounding box ，並不是相當容易還原排版，不過我處理的是選舉公報"},{"time":"1436362637.135","nick":"ⓢ kiang","msg":"選舉公報可能格式比較自由些，理論上文書轉出來的會精準些"},{"time":"1436362926.525","nick":"ⓢ mrorz","msg":"不過其實有 bounding box 資訊，或許是可以去掉重複的字沒錯"},{"time":"1436362927.488","nick":"ⓢ ↵","msg":"方塊字還滿方便的，行高 `yMax - yMin` 大概會跟字寬相等，因此兩個同行的 Box 的 `x` 重疊多少，就可以用 `yMax - yMin` 算出的字寬推出大概有幾個字重複"},{"time":"1436362962.541","nick":"ⓢ mrorz","msg":"anyway 先來嚐嚐 pdf2htmlEX (?)"},{"time":"1436363161.856","nick":"ⓢ mrorz","msg":"說到捷運時間，網路上之前有人批評過其實捷運公司非常常誤點，只是因為他沒公佈時刻表，所以沒有人知道它誤點了  xd"},{"time":"1436363254.384","nick":"CindyLinz","msg":"以前在教會認識在作捷運工程的哥哥, 他以前有跟我們說捷運站距太短很容易誤點, 因為沒有足夠距離調節車距.."},{"time":"1436363270.026","nick":"CindyLinz","msg":"應該不能說誤點, 是說班次很難準"},{"time":"1436363272.945","nick":"ⓢ chihao","msg":"因為沒有公開時刻表，就沒有「點」可以「誤」了 :stuck_out_tongue:"},{"time":"1436363277.873","nick":"CindyLinz","msg":"好像意思差不多 ^^|"},{"time":"1436363400.059","nick":"ⓢ mrorz","msg":"那捷運司機就會晚關門個幾秒來等慢慢走的旅客，是時間誤差的起點嗎～？"},{"time":"1436363422.156","nick":"ⓢ mrorz","msg":"然後因為每一站都要多等個幾秒，誤差就會一直累積下去 (?)"},{"time":"1436363634.902","nick":"CindyLinz","msg":"也有時候是等前一班......."},{"time":"1436363647.521","nick":"CindyLinz","msg":"尖峰時間車距太短怕危險 ^^|"},{"time":"1436363971.785","nick":"ⓢ chihao","msg":"可以像波士頓一樣停下來等前一輛車離站之後再開進去 :stuck_out_tongue:"},{"time":"1436364006.230","nick":"ⓢ mrorz","msg":"捷運有時候會這樣沒錯呀 XD"},{"time":"1436364045.840","nick":"ⓢ mrorz","msg":"台鐵區間車也常常停下來等別的車，不過是等自強號通過，好像不太一樣 |||"},{"time":"1436364318.113","nick":"ⓢ kiang","msg":"最神奇的還是日本吧，連公車時刻表都很準..."},{"time":"1436364392.290","nick":"ⓢ miaoski","msg":"@kiang: 然後常常開太快 (東京的 max 也是 40) 最後得要在站牌等時間"},{"time":"1436364483.315","nick":"ⓢ kiang","msg":"日本的公車經常在站牌等客人，時刻表的時間到了才會開走，而且有座位的時候司機會要求你坐下他才要開車，搞的我都覺得開公車是個很神聖的職業 XD"},{"time":"1436365376.446","nick":"ⓢ mrorz","msg":"會不會是日本的班次沒那麼密集，站與站之間的時間很充裕呢？"},{"time":"1436365411.434","nick":"ⓢ mrorz","msg":"應該是說班次表裡，站與站之間留下了足夠的時間"},{"time":"1436365897.053","nick":"ⓢ kiang","msg":"日本的公車在尖峰時段還是會遲到，但因為有時刻表，所以你只要那個時間點到，一定不會錯過那班車"},{"time":"1436366053.233","nick":"ⓢ kiang","msg":"在台南，即使你看著即時公車動態都有可能錯過公車，因為他如果看不到你就不會停下來 XD"},{"time":"1436366087.306","nick":"ⓢ mrorz","msg":"有道理 XD"},{"time":"1436366094.214","nick":"ⓢ kiang","msg":"所以台南適合慢遊，因為快不起來 XD"},{"time":"1436366220.468","nick":"ⓢ kiang","msg":"不過台灣有無敵的摩托車，所以感覺還是方便些（當然，建立在各種混亂交通的現況之上）"},{"time":"1436366876.137","nick":"ⓢ mrorz","msg":"pdf2htmlex 結果出爐："},{"time":"1436366877.131","nick":"ⓢ ↵","msg":"&lt;<a href=\"http://i.imgur.com/jMtuuyx.png\">http://i.imgur.com/jMtuuyx.png</a>&gt;"},{"time":"1436366878.357","nick":"ⓢ ↵","msg":"好像也很慘 orz"},{"time":"1436366879.138","nick":"ⓢ ↵","msg":"亮藍色底線的是我用滑鼠匡選的結果。滑鼠匡選可以呈現文字在 DOM 裡面的順序，看其來 DOM 裡面的文字是直的排的。如果把整個頁面用 innerText 倒出來，是完全不能讀的 orz"},{"time":"1436366995.600","nick":"ⓢ mrorz","msg":"這樣看起來，如果要做 text extraction 的話，比較合適的還是 pdftotext、開 bounding box，然後去算重複的字 orz"},{"time":"1436367000.902","nick":"CindyLinz","msg":"這字體好藝術...."},{"time":"1436367017.376","nick":"ⓢ mrorz","msg":"那個字體我完全不知道發生什麼事情 XDD"},{"time":"1436367038.403","nick":"ⓢ mrorz","msg":"pdf2htmlex 背後好像也有用到 pdftotext"},{"time":"1436367041.369","nick":"ⓢ au","msg":"那是 TTF bytecode，如果用 IE 看會是好的"},{"time":"1436367058.426","nick":"ⓢ au","msg":"（Safari Chrome Firefox 看各自都不一樣）"},{"time":"1436367265.629","nick":"ⓢ au","msg":"之前也有試過用 &lt;<a href=\"https://www.npmjs.com/package/pdf2json\">https://www.npmjs.com/package/pdf2json</a>&gt; 找 bounding box，結構同 `pdftotext` ，但是預先 parse 好的 &lt;<a href=\"https://github.com/audreyt/pdf2md/blob/master/parse.ls\">https://github.com/audreyt/pdf2md/blob/master/parse.ls</a>&gt;"},{"time":"1436367267.539","nick":"kcwu","msg":"slackbot3's url (2/2): [pdf2md/parse.ls at master · audreyt/pdf2md · GitHub]"},{"time":"1436367306.708","nick":"ⓢ mrorz","msg":"最後，pdf.js 則是這樣"},{"time":"1436367307.661","nick":"ⓢ ↵","msg":"&lt;<a href=\"http://i.imgur.com/BV7zlyZ.jpg\">http://i.imgur.com/BV7zlyZ.jpg</a>&gt;"},{"time":"1436367308.691","nick":"ⓢ ↵","msg":"字體不知道下了什麼魔法所以好很多（雖然好像有些被鬼遮眼）"},{"time":"1436367322.714","nick":"ⓢ mrorz","msg":"但是 object 一樣不符合閱讀順序"},{"time":"1436368260.830","nick":"ⓢ clkao","msg":"悲劇了 東西掉下來壓到鍵盤 在 inbox 裡把一堆待處理的信 archive 了........"},{"time":"1436368874.492","nick":"ⓢ michael_li","msg":"還好不是Delete　就會更悲劇（曾經苦主"},{"time":"1436369198.864","nick":"ⓢ mrorz","msg":"au: 感謝資訊 m(_ _)m"},{"time":"1436369199.904","nick":"ⓢ ↵","msg":"不過我發現 pdftotext 好像有先對 bounding box 的垂直位置與水平位置 sort 過，但 pdf2json 沒有的樣子"},{"time":"1436369200.858","nick":"ⓢ ↵","msg":"(左：`pdftotext -bbox`，右：pdf2json)"},{"time":"1436369201.892","nick":"ⓢ ↵","msg":"&lt;<a href=\"http://i.imgur.com/fY7pKrO.jpg\">http://i.imgur.com/fY7pKrO.jpg</a>&gt;"},{"time":"1436369202.871","nick":"ⓢ ↵","msg":"因為 pdf2json 是 port PDF.js（自幹 JS 版 PDF parser），所以跟 pdftotext 不一樣"},{"time":"1436369261.946","nick":"ⓢ mrorz","msg":"不過 sort json 超簡單的，應該會比 parse html 簡單很多 XD"},{"time":"1436369459.221","nick":"ⓢ mrorz","msg":"啊可是 pdftotext 有做多欄 detection 的樣子，好像不是只是單純地 sort bounding box position⋯⋯"},{"time":"1436370957.961","nick":"ⓢ au","msg":"mrorz++ # 確實是這樣，我記錯了。有用到 `pdftotext` 的是 &lt;<a href=\"https://github.com/audreyt/pdf2line\">https://github.com/audreyt/pdf2line</a>&gt; 不是 pdf2md"},{"time":"1436370959.818","nick":"kcwu","msg":"slackbot3's url: [audreyt/pdf2line · GitHub]"}]