[{"time":"1441821862.187","nick":"wrigic2","msg":"clkao ronnywang: (關於logbot 9/7 # 5) 我要的是 logbot 9/7 # 12 所描述的，如果可以的話是否可以把資料集dump然後上傳到網路空間，有時間我在到網路空間自行下載。謝謝。"},{"time":"1441850430.912","nick":"ⓢ mrorz","msg":"saul511++"},{"time":"1441852105.746","nick":"macpaul1","msg":"etblue: 大松器材是有streaming的那個盒子嘛？"},{"time":"1441853444.212","nick":"ⓢ billy3321","msg":"&lt;<a href=\"https://github.com/rubytaiwan/taipei\">https://github.com/rubytaiwan/taipei</a>&gt;"},{"time":"1441853446.363","nick":"kcwu_","msg":"slackbot2's url: [rubytaiwan/taipei · GitHub]"},{"time":"1441853461.231","nick":"ⓢ billy3321","msg":"剛剛偶然看到rubyconf做了這個台北導覽handbook"},{"time":"1441853477.260","nick":"ⓢ billy3321","msg":"g0v要不要fork一個，大家一起共筆，未來有人來台參訪都可以用？"},{"time":"1441853936.533","nick":"AceLan","msg":"billy3321: 讚!!!"},{"time":"1441856039.103","nick":"ⓢ etblue","msg":"macpaul: 是上次在你旁邊用的 wirecast + ipad，然後我昨天回家才想到，我忘記確認現場的直播專用 wifi 是不是 5G 了，可能因此導致訊號不穩 XDrz"},{"time":"1441856052.130","nick":"ⓢ etblue","msg":"macpaul: 對了，你們覺得 OBS 怎樣？據說 CPU loading 比 wirecast 小很多？ cc yhsiang"},{"time":"1441856458.569","nick":"ⓢ yhsiang","msg":"Etblue: 很爛"},{"time":"1441856503.625","nick":"ⓢ etblue","msg":"yhsiang: 真假？！昨天台北國際會議中心的阿宅工程師說他都用OBS直播diablo..."},{"time":"1441856552.667","nick":"ⓢ yhsiang","msg":"認真說 很爛 XD"},{"time":"1441856560.694","nick":"ⓢ etblue","msg":"www"},{"time":"1441856579.699","nick":"ⓢ yhsiang","msg":"但是是open source solution"},{"time":"1441856583.701","nick":"ⓢ yhsiang","msg":"XDDD"},{"time":"1441856604.722","nick":"ⓢ etblue","msg":"難怪介面有點醜（喂"},{"time":"1441856982.150","nick":"ⓢ clkao","msg":"wrigic2: hi, localdata census dump 在這裡: &lt;<a href=\"https://docs.google.com/spreadsheets/d/1W-0i_n0flamQYkFYvIZWWaWUJCfWJTkehEK5pEc5Uy0/edit#gid=0\">https://docs.google.com/spreadsheets/d/1W-0i_n0flamQYkFYvIZWWaWUJCfWJTkehEK5pEc5Uy0/edit#gid=0</a>&gt;"},{"time":"1441856984.265","nick":"kcwu_","msg":"slackbot2's url: [TW Open Data Census 2014 Dump - Google 試算表]"},{"time":"1441857282.486","nick":"ⓢ pofeng","msg":"@clkao: 關於 @kiang 的狀況我很樂意幫忙問一下啊 (雖然沒把握)  但是被告很麻煩, 我覺得 @kiang 不一定願意抵抗到底"},{"time":"1441857752.999","nick":"ⓢ clkao","msg":"問 tahr/jrf 的話就不是要特定 project 抵抗到底的意思了。而是這些 public info 任何人都可以用寫好的 open source 工具 republish，這點應該要被保障"},{"time":"1441858843.174","nick":"ⓢ rschiang","msg":"@pofeng: @clkao: 好奇 <a href=\"http://foundations.olc.tw\">http://foundations.olc.tw</a> 為甚麼會有被告的風險(?)"},{"time":"1441858845.284","nick":"kcwu_","msg":"slackbot2's url: [法人一覽 @ 社團/財團法人資料檢索]"},{"time":"1441859129.478","nick":"ⓢ pofeng","msg":"可能是我想太多啦, 不過  @kiang 那邊已經有收到兩個希望資料移除的要求"},{"time":"1441859176.528","nick":"ⓢ pofeng","msg":"有時候告人只是手段, 或許提告人也知道沒用 但總是會給人(被告)壓力"},{"time":"1441859208.563","nick":"ⓢ billy3321","msg":"@pofeng: 我這邊應該可以找律師來幫忙"},{"time":"1441859233.593","nick":"ⓢ billy3321","msg":"但問題是，我認識的律師好像在台北執業，要幫 @kiang 的話，應該要台南執業的律師？"},{"time":"1441859343.724","nick":"ⓢ kiang","msg":"目前還沒有被告的前兆啦，只是 google 加入索引後很多人不想要讓人知道的資訊變得容易出現"},{"time":"1441859409.807","nick":"ⓢ pofeng","msg":"@clkao: 也對, 有具體建議的下一步嗎 ? ( 宣傳 ? 修法 ?  提告取得判例 or ... ? )"},{"time":"1441859470.868","nick":"ⓢ pofeng","msg":"@billy3321:  好喔, 有需要會找你們 :stuck_out_tongue:"},{"time":"1441859518.912","nick":"ⓢ pofeng","msg":"@kiang: 比較怕有人主張被遺忘權 ..."},{"time":"1441859575.003","nick":"ⓢ kiang","msg":"政府公開資訊可以這樣主張？"},{"time":"1441859658.074","nick":"ⓢ au","msg":"在台灣目前不行，在歐盟則可以 （移除搜尋引擎索引，不是移除資料網頁本身）"},{"time":"1441859673.080","nick":"ⓢ clkao","msg":"歷史資料可能比較會有爭議。現況的我是認為不可能主張，因為是依法要公告的資訊。"},{"time":"1441860819.350","nick":"ⓢ au","msg":"&lt;<a href=\"http://join.gov.tw/openup/idea/\">http://join.gov.tw/openup/idea/</a>&gt; NDC 的「提點子」上線了，先試玩兩個月，明年選後再重啟~"},{"time":"1441860820.034","nick":"kcwu_","msg":"slackbot2's url: [公共政策網路參與平台 - 提點子]"},{"time":"1441861020.568","nick":"ⓢ kiang","msg":"au: 有 api 可以備份嗎？ XD"},{"time":"1441861427.004","nick":"ⓢ au","msg":"目前已經後台有給部會的 api，但前台也應該開放或至少給 data dump..."},{"time":"1441861503.685","nick":"ronnywang","msg":"kiang: 還是先加上 robots.txt 先讓 google 找不到"},{"time":"1441861594.175","nick":"ⓢ kiang","msg":"ronnywang: 可是做這個的目的就是希望大家找的到啊 XD ，如果找不到就維持原本透過法院系統即可，那邊有設定不讓 google 檢索 XD"},{"time":"1441861740.693","nick":"Jedi_","msg":"「我們本來以為公開的意思是：我們的東西放出來但是你都找不到，你的東西自以為沒放出來但是我們都可以拿來賣錢」"},{"time":"1441861778.450","nick":"Jedi_","msg":"&lt;/設計對白&gt;"},{"time":"1441862002.644","nick":"ronnywang","msg":"不過法人的董監事或資本額變更後，舊資料在原來法院上還查的到嗎?"},{"time":"1441862002.911","nick":"ronnywang","msg":"如果還查的到，那法律上應該就沒什麼問題，本來就是公開資料了"},{"time":"1441862057.665","nick":"ⓢ kiang","msg":"ronnywang: 應該還是查的到的，因為 &lt;<a href=\"https://github.com/g0v/foundationtw\">https://github.com/g0v/foundationtw</a>&gt; 2014 才開始運作，早期的資料一樣都是從法院網站拉下來"},{"time":"1441862059.683","nick":"kcwu_","msg":"slackbot2's url: [g0v/foundationtw · GitHub]"},{"time":"1441862137.765","nick":"ⓢ kiang","msg":"很多資料無法 grouping 的原因也就是名稱改變，登記字號混亂的情況沒辦法處理 XD"},{"time":"1441863623.398","nick":"ⓢ kiang","msg":"&lt;<a href=\"http://www.gov.taipei/ct.asp?xItem=116828632&amp;amp;ctNode=5158&amp;amp;mp=100001\">http://www.gov.taipei/ct.asp?xItem=116828632&amp;amp;ctNode=5158&amp;amp;mp=100001</a>&gt; - 有人要去湊熱鬧嗎？ :simple_smile:"},{"time":"1441863869.836","nick":"ⓢ au","msg":"kiang: 我拿你的 api 備份想法測「提點子」了，目前檢核中 XD &lt;<a href=\"https://gist.github.com/audreyt/3214ae84c217341770e9\">https://gist.github.com/audreyt/3214ae84c217341770e9</a>&gt;"},{"time":"1441863871.658","nick":"kcwu_","msg":"slackbot2's url: [join-idea.md · GitHub]"},{"time":"1441863878.672","nick":"ⓢ kiang","msg":"au++"},{"time":"1441863880.680","nick":"ⓢ au","msg":"undefined"},{"time":"1441864856.581","nick":"binith","msg":"@@"},{"time":"1441866391.434","nick":"ⓢ kiang","msg":"au: 踹了一下，畫面顯示送出失敗，但是卻收到通知信說 已進入檢核階段 XD"},{"time":"1441866424.475","nick":"ⓢ au","msg":"kiang: POST //join.gov.tw/openup/idea/propose/update-status 會 503，已向聯經數位回報，他們正在搶修 XD"},{"time":"1441866434.484","nick":"ⓢ au","msg":"修好之後再重新送出"},{"time":"1441866796.888","nick":"ⓢ kiang","msg":"備份： &lt;<a href=\"https://gist.github.com/kiang/7948cac6f8a3dab6e285\">https://gist.github.com/kiang/7948cac6f8a3dab6e285</a>&gt; ，就看後續囉"},{"time":"1441869059.339","nick":"ⓢ kiang","msg":"解開一個送 bug report 然後接到美女客服來電關心的成就"},{"time":"1441869096.400","nick":"ⓢ yurenju","msg":"@kiang: 你怎麼知道是美女 XD"},{"time":"1441869122.408","nick":"ⓢ kiang","msg":"yurenju: 宅男的幻想世界不是一般人能夠理解的"},{"time":"1441871115.606","nick":"ⓢ davihuan","msg":"@@ 激勵工程師的作用?"},{"time":"1441874460.263","nick":"ⓢ jimyhuang","msg":"ronnywang: 法院登記資料不只查的到，法院登記還有歷來變更的備份。每一次變更都要公示"},{"time":"1441876384.374","nick":"ⓢ au","msg":"kiang: 似乎後台修好了 &lt;<a href=\"http://join.gov.tw/openup/idea/detail/25824c17-f141-447a-82f9-ea9f4b6b69d4\">http://join.gov.tw/openup/idea/detail/25824c17-f141-447a-82f9-ea9f4b6b69d4</a>&gt;"},{"time":"1441876385.113","nick":"kcwu_","msg":"slackbot2's url: [公共政策網路參與平台 - 提點子-Join 平台應提供匯出資料供批次下載]"},{"time":"1441892608.197","nick":"ⓢ kiang","msg":"jimyhuang: 可是個別資料之間很難串起來 XD"},{"time":"1441892646.240","nick":"ⓢ kiang","msg":"au: 我的還沒通過審核，不知道繼續踹這個頁面會有什麼新發現 - &lt;<a href=\"http://join.gov.tw/openup/idea/detail/b02f2043-f826-42ff-b6e1-8b21df312bea\">http://join.gov.tw/openup/idea/detail/b02f2043-f826-42ff-b6e1-8b21df312bea</a>&gt;"},{"time":"1441894551.333","nick":"ⓢ pofeng","msg":"好好笑 FB 登錄完不會回到 join 平台 :stuck_out_tongue:"},{"time":"1441900317.643","nick":"ⓢ clkao","msg":"hlb: 好像要想一下 g0v.cafe 文案... 「你知道過去十五個月來，只有五個人帶咖啡到黑客松嗎？」"},{"time":"1441900388.717","nick":"ⓢ clkao","msg":"「黑客松怎麼可以沒有自己的咖啡」"}]